__init__.py
atfu.py
atfu/__init__.py
atfu/check.py
atfu/command.py
atfu/device_id.py
atfu/erase.py
atfu/output.py
atfu/program.py
atfu/programmer.py
atfu/verify.py
atfu/converter/device.py
atfu/converter/fuseconv.py
atfu/converter/jed2svf.py
atfu/converter/jesd3.py
atfu/converter/svf2xsvf.py
atfu/converter/svfeventhandler.py
atfu/little_board/jtag_programmer.py
atfu/standard_vectors/__init__.py
atfu/standard_vectors/bc1502.xsvf
atfu/standard_vectors/bc1502v.xsvf
atfu/standard_vectors/bc1504.xsvf
atfu/standard_vectors/bc1504v.xsvf
atfu/standard_vectors/bc1508.xsvf
atfu/standard_vectors/bc1508v.xsvf
atfu/standard_vectors/e1502.xsvf
atfu/standard_vectors/e1502v.xsvf
atfu/standard_vectors/e1504.xsvf
atfu/standard_vectors/e1504v.xsvf
atfu/standard_vectors/e1508.xsvf
atfu/standard_vectors/e1508v.xsvf
little_atf_programmer-2025.1024.dist-info/licenses/LICENSE.md
little_atf_programmer-2025.1024.dist-info/METADATA
little_atf_programmer-2025.1024.dist-info/WHEEL
little_atf_programmer-2025.1024.dist-info/entry_points.txt
little_atf_programmer-2025.1024.dist-info/top_level.txt
little_atf_programmer-2025.1024.dist-info/RECORD
