Metadata-Version: 2.4
Name: little-atf-programmer
Version: 2025.1024
Summary: Little ATF150x Programmer Board utility programs
Author-email: The Really Old-School Company Limited <info@rosco-m68k.com>
License: Copyright (c) 2024 The Really Old-School Company Limited
Project-URL: Homepage, https://github.com/roscopeco/atfprog-tools
Keywords: cpld,atf1502,atf1504,atf1508,logic,programmer
Classifier: License :: OSI Approved :: MIT License
Classifier: Programming Language :: Python
Classifier: Programming Language :: Python :: 3
Requires-Python: >=3.9
License-File: LICENSE.md
Requires-Dist: pyserial==3.5
Requires-Dist: pyparsing==3.1.2
Requires-Dist: bitarray==2.9.2
Requires-Dist: tabulate==0.9.0
Requires-Dist: progress==1.6
Requires-Dist: tqdm==4.66.2
Provides-Extra: dev
Requires-Dist: black; extra == "dev"
Requires-Dist: bumpver; extra == "dev"
Requires-Dist: pre-commit; extra == "dev"
Requires-Dist: isort; extra == "dev"
Requires-Dist: pip-tools; extra == "dev"
Requires-Dist: pytest; extra == "dev"
Requires-Dist: sure; extra == "dev"
Requires-Dist: httpretty; extra == "dev"
Dynamic: license-file
